GeoFuns/__init__.py
GeoFuns/geo_queries.py
GeoFuns/geofunctions.py
GeoFuns/places.py
GeoFuns-1.1.8.dist-info/METADATA
GeoFuns-1.1.8.dist-info/WHEEL
GeoFuns-1.1.8.dist-info/top_level.txt
GeoFuns-1.1.8.dist-info/RECORD
