Metadata-Version: 2.1
Name: GeoFuns
Version: 1.1.8
Summary: A package for geo tools used to map card score
Home-page: https://github.com/harryritchie/Landkarte
Author: Harry Ritchie
Author-email: harry.ritchie@prea.eu
License: UNKNOWN
Platform: UNKNOWN
Classifier: Programming Language :: Python :: 3
Classifier: License :: OSI Approved :: MIT License
Classifier: Operating System :: OS Independent
Requires-Python: >=3.6
Requires-Dist: affine (==2.3.0)
Requires-Dist: appnope (==0.1.0)
Requires-Dist: attrs (==19.3.0)
Requires-Dist: backcall (==0.1.0)
Requires-Dist: beautifulsoup4 (==4.9.0)
Requires-Dist: bleach (==3.1.4)
Requires-Dist: bs4 (==0.0.1)
Requires-Dist: cachetools (==4.1.0)
Requires-Dist: certifi (==2020.4.5.1)
Requires-Dist: chardet (==3.0.4)
Requires-Dist: click (==7.1.1)
Requires-Dist: click-plugins (==1.1.1)
Requires-Dist: cligj (==0.5.0)
Requires-Dist: cycler (==0.10.0)
Requires-Dist: decorator (==4.4.2)
Requires-Dist: defusedxml (==0.6.0)
Requires-Dist: Deprecated (==1.2.9)
Requires-Dist: descartes (==1.1.0)
Requires-Dist: entrypoints (==0.3)
Requires-Dist: esda (==2.2.1)
Requires-Dist: Fiona (==1.8.13.post1)
Requires-Dist: geojson (==2.5.0)
Requires-Dist: geopandas (==0.7.0)
Requires-Dist: giddy (==2.3.0)
Requires-Dist: gmaps (==0.9.0)
Requires-Dist: google-api-core (==1.17.0)
Requires-Dist: google-auth (==1.14.1)
Requires-Dist: google-auth-oauthlib (==0.4.1)
Requires-Dist: google-cloud-bigquery (==1.24.0)
Requires-Dist: google-cloud-core (==1.3.0)
Requires-Dist: google-resumable-media (==0.5.0)
Requires-Dist: googleapis-common-protos (==1.51.0)
Requires-Dist: googlemaps (==4.2.0)
Requires-Dist: idna (==2.9)
Requires-Dist: importlib-metadata (==1.6.0)
Requires-Dist: inequality (==1.0.0)
Requires-Dist: ipykernel (==5.2.1)
Requires-Dist: ipython (==7.13.0)
Requires-Dist: ipython-genutils (==0.2.0)
Requires-Dist: ipywidgets (==7.5.1)
Requires-Dist: jedi (==0.17.0)
Requires-Dist: Jinja2 (==2.11.2)
Requires-Dist: joblib (==0.14.1)
Requires-Dist: jsonschema (==3.2.0)
Requires-Dist: jupyter-client (==6.1.3)
Requires-Dist: jupyter-core (==4.6.3)
Requires-Dist: kiwisolver (==1.2.0)
Requires-Dist: libpysal (==4.2.2)
Requires-Dist: llvmlite (==0.32.0)
Requires-Dist: mapclassify (==2.2.0)
Requires-Dist: MarkupSafe (==1.1.1)
Requires-Dist: matplotlib (==3.2.1)
Requires-Dist: mgwr (==2.1.1)
Requires-Dist: mistune (==0.8.4)
Requires-Dist: mpmath (==1.1.0)
Requires-Dist: munch (==2.5.0)
Requires-Dist: nbconvert (==5.6.1)
Requires-Dist: nbformat (==5.0.6)
Requires-Dist: notebook (==6.0.3)
Requires-Dist: numba (==0.49.0)
Requires-Dist: numpy (==1.18.3)
Requires-Dist: oauthlib (==3.1.0)
Requires-Dist: pandas (==1.0.3)
Requires-Dist: pandas-gbq (==0.13.1)
Requires-Dist: pandocfilters (==1.4.2)
Requires-Dist: parso (==0.7.0)
Requires-Dist: patsy (==0.5.1)
Requires-Dist: pexpect (==4.8.0)
Requires-Dist: pickleshare (==0.7.5)
Requires-Dist: pointpats (==2.1.0)
Requires-Dist: prometheus-client (==0.7.1)
Requires-Dist: prompt-toolkit (==3.0.5)
Requires-Dist: protobuf (==3.11.3)
Requires-Dist: ptyprocess (==0.6.0)
Requires-Dist: pyasn1 (==0.4.8)
Requires-Dist: pyasn1-modules (==0.2.8)
Requires-Dist: pydata-google-auth (==1.0.0)
Requires-Dist: Pygments (==2.6.1)
Requires-Dist: pyparsing (==2.4.7)
Requires-Dist: pyproj (==2.6.0)
Requires-Dist: pyrsistent (==0.16.0)
Requires-Dist: pysal (==2.2.0)
Requires-Dist: python-dateutil (==2.8.0)
Requires-Dist: pytz (==2019.3)
Requires-Dist: pyzmq (==19.0.0)
Requires-Dist: quantecon (==0.4.6)
Requires-Dist: rasterio (==1.1.3)
Requires-Dist: rasterstats (==0.14.0)
Requires-Dist: requests (==2.23.0)
Requires-Dist: requests-oauthlib (==1.3.0)
Requires-Dist: rsa (==4.0)
Requires-Dist: Rtree (==0.9.4)
Requires-Dist: scikit-learn (==0.22.2.post1)
Requires-Dist: scipy (==1.4.1)
Requires-Dist: seaborn (==0.10.0)
Requires-Dist: segregation (==1.2.0)
Requires-Dist: Send2Trash (==1.5.0)
Requires-Dist: Shapely (==1.7.0)
Requires-Dist: simplejson (==3.17.0)
Requires-Dist: six (==1.14.0)
Requires-Dist: snuggs (==1.4.7)
Requires-Dist: soupsieve (==2.0)
Requires-Dist: spaghetti (==1.4.2.post2)
Requires-Dist: spglm (==1.0.7)
Requires-Dist: spint (==1.0.6)
Requires-Dist: splot (==1.1.3)
Requires-Dist: spreg (==1.1.1)
Requires-Dist: spvcm (==0.3.0)
Requires-Dist: statsmodels (==0.11.1)
Requires-Dist: sympy (==1.5.1)
Requires-Dist: terminado (==0.8.3)
Requires-Dist: testpath (==0.4.4)
Requires-Dist: tobler (==0.3.0)
Requires-Dist: tornado (==6.0.4)
Requires-Dist: tqdm (==4.45.0)
Requires-Dist: traitlets (==4.3.3)
Requires-Dist: urllib3 (==1.24.3)
Requires-Dist: watermark (==2.0.2)
Requires-Dist: wcwidth (==0.1.9)
Requires-Dist: webencodings (==0.5.1)
Requires-Dist: widgetsnbextension (==3.5.1)
Requires-Dist: wrapt (==1.12.1)
Requires-Dist: zipp (==3.1.0)
